practicusai/__init__.py
practicusaicore/__init__.py
practicusainode/__init__.py
practicusnode/__init__.py
practicusainode-0.0.1.dist-info/METADATA
practicusainode-0.0.1.dist-info/WHEEL
practicusainode-0.0.1.dist-info/top_level.txt
practicusainode-0.0.1.dist-info/RECORD
